{
    "fluentMethods": true,
    "relationships": [],
    "fields": [
        {
            "fieldName": "aporte",
            "fieldType": "String"
        },
        {
            "fieldName": "idreferencia",
            "fieldType": "Integer"
        },
        {
            "fieldName": "moeda",
            "fieldType": "String"
        },
        {
            "fieldName": "nreferencia",
            "fieldType": "Integer"
        },
        {
            "fieldName": "valorreferencia",
            "fieldType": "BigDecimal"
        }
    ],
    "changelogDate": "20170607001907",
    "entityTableName": "referencia",
    "dto": "mapstruct",
    "pagination": "no",
    "service": "no",
    "angularJSSuffix": "ambiental"
}